edo/__init__.py
edo/family.py
edo/fitness.py
edo/individual.py
edo/optimiser.py
edo/population.py
edo/version.py
edo/distributions/__init__.py
edo/distributions/base.py
edo/distributions/continuous.py
edo/distributions/discrete.py
edo/operators/__init__.py
edo/operators/crossover.py
edo/operators/mutation.py
edo/operators/selection.py
edo/operators/shrink.py
edo/operators/util.py
edo-0.3.6.dist-info/LICENSE
edo-0.3.6.dist-info/METADATA
edo-0.3.6.dist-info/WHEEL
edo-0.3.6.dist-info/top_level.txt
edo-0.3.6.dist-info/RECORD
