Metadata-Version: 2.1
Name: edo
Version: 0.3.6
Summary: Generating artificial datasets through evolution.
Home-page: https://github.com/daffidwilde/edo
Author: Henry Wilde, Vincent Knight, Jonathan Gillard
Author-email: henrydavidwilde@gmail.com
License: MIT
Keywords: evolutionary algorithm,artificial data,evolution
Platform: UNKNOWN
Requires-Python: >=3.6
Requires-Dist: dask[dataframe] (==2.30.0)
Requires-Dist: numpy
Requires-Dist: pandas
